LICENSE
MANIFEST.in
README.rst
setup.cfg
setup.py
siftlog/__init__.py
siftlog.egg-info/PKG-INFO
siftlog.egg-info/SOURCES.txt
siftlog.egg-info/dependency_links.txt
siftlog.egg-info/not-zip-safe
siftlog.egg-info/top_level.txt