Metadata-Version: 2.1
Name: siftlog
Version: 0.22
Summary: [DEPRECATED] Structured JSON logging
Home-page: http://github.com/papito/siftlog-py
Author: Andrei Taranchenko
Author-email: andrei360-git@yahoo.com
License: MIT
Platform: UNKNOWN
License-File: LICENSE
